setup.py
src/digimat/__init__.py
src/digimat.ebus.egg-info/PKG-INFO
src/digimat.ebus.egg-info/SOURCES.txt
src/digimat.ebus.egg-info/dependency_links.txt
src/digimat.ebus.egg-info/namespace_packages.txt
src/digimat.ebus.egg-info/not-zip-safe
src/digimat.ebus.egg-info/requires.txt
src/digimat.ebus.egg-info/top_level.txt
src/digimat/ebus/__init__.py
src/digimat/ebus/ebus.py