Metadata-Version: 1.0
Name: digimat.ebus
Version: 0.1.12
Summary: Digimat ExternalBus
Home-page: http://www.digimat.ch
Author: Frederic Hess
Author-email: fhess@splust.ch
License: PSF
Platform: UNKNOWN
